MANIFEST.in
README.rst
setup.cfg
setup.py
ckanext/__init__.py
ckanext/ands/__init__.py
ckanext/ands/auth.py
ckanext/ands/controller.py
ckanext/ands/helpers.py
ckanext/ands/model.py
ckanext/ands/plugin.py
ckanext/ands/templates/package/doi.html
ckanext/ands/templates/package/doi_admin.html
ckanext/ands/templates/package/doi_email.text
ckanext/ands/templates/package/doi_request_completed.text
ckanext/ands/templates/package/read.html
ckanext/ands/templates/package/read_base.html
ckanext/ands/templates/snippets/package_citation.html
ckanext/ands/tests/__init__.py
ckanext/ands/tests/test_plugin.py
ckanext_ands.egg-info/PKG-INFO
ckanext_ands.egg-info/SOURCES.txt
ckanext_ands.egg-info/dependency_links.txt
ckanext_ands.egg-info/entry_points.txt
ckanext_ands.egg-info/pbr.json
ckanext_ands.egg-info/requires.txt
ckanext_ands.egg-info/top_level.txt