Metadata-Version: 1.1
Name: ckanext-ands
Version: 0.0.7
Summary: Mints DOI ids using ANDS
Home-page: https://github.com/Psykar/ckanext-ands
Author: Louis des Landes
Author-email: ldeslandes@swin.edu.au
License: AGPL
Keywords: CKAN DOI ANDS external id
Platform: UNKNOWN
Classifier: Development Status :: 4 - Beta
Classifier: License :: OSI Approved :: GNU Affero General Public License v3 or later (AGPLv3+)
Classifier: Programming Language :: Python :: 2.6
Classifier: Programming Language :: Python :: 2.7
